{
  "id": "3502422",
  "name": "hkzf",
  "font_family": "iconfont",
  "css_prefix_text": "icon-",
  "description": "",
  "glyphs": [
    {
      "icon_id": "493476",
      "name": "个人",
      "font_class": "geren",
      "unicode": "e7a3",
      "unicode_decimal": 59299
    },
    {
      "icon_id": "658040",
      "name": "收藏",
      "font_class": "shoucang",
      "unicode": "e666",
      "unicode_decimal": 58982
    },
    {
      "icon_id": "765262",
      "name": "首页",
      "font_class": "shouye",
      "unicode": "e612",
      "unicode_decimal": 58898
    },
    {
      "icon_id": "1159868",
      "name": "房产房子",
      "font_class": "fangchanfangzi",
      "unicode": "e604",
      "unicode_decimal": 58884
    },
    {
      "icon_id": "2170917",
      "name": "地图找房",
      "font_class": "dituzhaofang",
      "unicode": "e603",
      "unicode_decimal": 58883
    },
    {
      "icon_id": "2674476",
      "name": "客服",
      "font_class": "kefu",
      "unicode": "e625",
      "unicode_decimal": 58917
    },
    {
      "icon_id": "3512020",
      "name": "收房量房",
      "font_class": "shoufangliangfang",
      "unicode": "e63c",
      "unicode_decimal": 58940
    },
    {
      "icon_id": "4055804",
      "name": "房子",
      "font_class": "fangzi",
      "unicode": "e8ff",
      "unicode_decimal": 59647
    },
    {
      "icon_id": "4166140",
      "name": "朋友",
      "font_class": "pengyou",
      "unicode": "e61a",
      "unicode_decimal": 58906
    },
    {
      "icon_id": "11372646",
      "name": "播放记录",
      "font_class": "bofangjilu",
      "unicode": "e8ad",
      "unicode_decimal": 59565
    },
    {
      "icon_id": "11372655",
      "name": "地图",
      "font_class": "ditu",
      "unicode": "e8ae",
      "unicode_decimal": 59566
    },
    {
      "icon_id": "11488079",
      "name": "namecard",
      "font_class": "namecard",
      "unicode": "e759",
      "unicode_decimal": 59225
    },
    {
      "icon_id": "12387155",
      "name": "资讯",
      "font_class": "zixun",
      "unicode": "e90d",
      "unicode_decimal": 59661
    },
    {
      "icon_id": "13604659",
      "name": "查找",
      "font_class": "chazhao",
      "unicode": "e656",
      "unicode_decimal": 58966
    }
  ]
}
